<annotation>
  <folder>KAIST Multispectral Ped Benchmark</folder>
  <filename>set02/V001/I00971</filename>
  <source>
    <database>KAIST pedestrian</database>
    <annotation>KAIST pedestrian</annotation>
    <image>KAIST pedestrian</image>
    <url>https://soonminhwang.github.io/rgbt-ped-detection/</url>
  </source>
  <size>
    <width>640</width>
    <height>512</height>
    <depth>4</depth>
  </size>
  <segmented>0</segmented>
  <object>
    <name>person</name>
    <bndbox>
      <x>548</x>
      <y>249</y>
      <w>74</w>
      <h>243</h>
    </bndbox>
    <pose>unknown</pose>
    <truncated>0</truncated>
    <difficult>0</difficult>
    <occlusion>0</occlusion>
  </object>
  <object>
    <name>person</name>
    <bndbox>
      <x>494</x>
      <y>228</y>
      <w>86</w>
      <h>222</h>
    </bndbox>
    <pose>unknown</pose>
    <truncated>0</truncated>
    <difficult>0</difficult>
    <occlusion>0</occlusion>
  </object>
</annotation>
